[{"id":"ENGL1100","name":"Lit., Law, and Criminality","code":"1100","departmentId":"ENGL"},{"id":"ENGL2100","name":"Topics in Popular Culture","code":"2100","departmentId":"ENGL"},{"id":"ENGL2500","name":"Classical Mythology","code":"2500","departmentId":"ENGL"},{"id":"ENGL3501","name":"Lit. and Cultures 1900-Now","code":"3501","departmentId":"ENGL"},{"id":"ENGL3605","name":"Modern/Contemp Literary Theory","code":"3605","departmentId":"ENGL"},{"id":"ENGL4115","name":"Culture & the Text","code":"4115","departmentId":"ENGL"},{"id":"ENGL4115","name":"Culture & the Text","code":"4115","departmentId":"ENGL"},{"id":"ENGL4301","name":"Studies in Renaissance Lit.","code":"4301","departmentId":"ENGL"},{"id":"ENGL4609","name":"Global Stages and Theories","code":"4609","departmentId":"ENGL"},{"id":"ENGL5120","name":"Book Arts Workshop","code":"5120","departmentId":"ENGL"},{"id":"ENGL5900","name":"Sel. Topic English Studies I","code":"5900","departmentId":"ENGL"},{"id":"ENGL5900","name":"Sel. Topic English Studies I","code":"5900","departmentId":"ENGL"},{"id":"ENGL5901","name":"Sel. Topic English Studies II","code":"5901","departmentId":"ENGL"},{"id":"ENGL5908","name":"Research Essay","code":"5908","departmentId":"ENGL"},{"id":"ENGL5909","name":"M.A. Thesis","code":"5909","departmentId":"ENGL"},{"id":"ENGL6101","name":"Directed Reading","code":"6101","departmentId":"ENGL"},{"id":"ENGL6900","name":"Comprehensive Examination","code":"6900","departmentId":"ENGL"},{"id":"ENGL6909","name":"Thesis","code":"6909","departmentId":"ENGL"}]