[{"id":"SREE3001-A","courseId":"SREE3001","section":"A","term":"","type":"Lecture","startDate":"2023-09-06","endDate":"2023-12-08","days":[{"day":[],"startTime":"","endTime":"","building":"","room":""},{"day":["Mon","Wed"],"startTime":"14:35","endTime":"15:55","building":" Teraanga Commons (former CO)","room":" 213"}],"staffId":"kristen-schell","physicality":"IN-PERSON","registrationAdditions":[" SREE 3001 L1"]},{"id":"SREE3001-B","courseId":"SREE3001","section":"B","term":"","type":"Lecture","startDate":"2023-09-06","endDate":"2023-12-08","days":[{"day":[],"startTime":"","endTime":"","building":"","room":""},{"day":["Mon","Wed"],"startTime":"14:35","endTime":"15:55","building":" Teraanga Commons (former CO)","room":" 213"}],"staffId":"kristen-schell","physicality":"IN-PERSON","registrationAdditions":[" SREE 3001 L1"]},{"id":"SREE3001-L1","courseId":"SREE3001","section":"L1","term":"","type":"Laboratory","startDate":"2023-09-06","endDate":"2023-12-08","days":[{"day":[],"startTime":"","endTime":"","building":"","room":""},{"day":["Tue"],"startTime":"16:35","endTime":"17:25","building":" Mackenzie Building","room":" 3174"}],"staffId":"kristen-schell","physicality":"IN-PERSON","registrationAdditions":[" SREE 3001 A or B"]},{"id":"SREE4001-A","courseId":"SREE4001","section":"A","term":"","type":"Lecture","startDate":"2023-09-06","endDate":"2023-12-08","days":[{"day":[],"startTime":"","endTime":"","building":"","room":""},{"day":["Mon","Wed"],"startTime":"11:35","endTime":"12:55","building":" Teraanga Commons (former CO)","room":" 208"}],"staffId":"kristen-schell","physicality":"IN-PERSON","registrationAdditions":[" SREE 4001 L1"]},{"id":"SREE4001-L1","courseId":"SREE4001","section":"L1","term":"","type":"Laboratory","startDate":"2023-09-06","endDate":"2023-12-08","days":[{"day":[],"startTime":"","endTime":"","building":"","room":""},{"day":["Thu"],"startTime":"14:35","endTime":"17:25","building":" Canal Building","room":" 2104"}],"staffId":"kristen-schell","physicality":"IN-PERSON","registrationAdditions":[" SREE 4001 A"]},{"id":"SREE4907-A","courseId":"SREE4907","section":"A","term":"","type":"Independent Study","startDate":"2023-09-06","endDate":"2023-12-08","days":[{"day":[],"startTime":"","endTime":"","building":"","room":""},{"day":[""],"startTime":null,"endTime":null,"building":null,"room":null}],"staffId":" ","physicality":"ONLINE","registrationAdditions":[]}]