[{"name":"Beth Goslett","id":"beth-goslett"},{"name":"Neil Mispelaar","id":"neil-mispelaar"},{"name":"Joanne MacDonald","id":"joanne-macdonald"},{"name":"Helena Merriam","id":"helena-merriam"},{"name":"Samantha Thompson","id":"samantha-thompson"},{"name":"Erika Fyfe","id":"erika-fyfe"},{"name":"Masoud Barati","id":"masoud-barati"},{"name":"Hosna Hamdieh","id":"hosna-hamdieh"},{"name":"Emily Austin","id":"emily-austin"},{"name":"Michael Kent","id":"michael-kent"},{"name":"Jie Gao","id":"jie-gao"},{"name":"Omair Shafiq","id":"omair-shafiq"},{"name":"Linda Pasquale","id":"linda-pasquale"},{"name":"John Keenan","id":"john-keenan"},{"name":"David Sprague","id":"david-sprague"},{"name":"James Brunet","id":"james-brunet"},{"name":"Chris Trainor","id":"chris-trainor"},{"name":"Nader Naseri Joojili","id":"nader-naseri-joojili"}]