[{"name":"Dr George Pollard","id":"dr-george-pollard"},{"name":"Phillip Primeau","id":"phillip-primeau"},{"name":"Steven Prus","id":"steven-prus"},{"name":"Mike Mopas","id":"mike-mopas"},{"name":"Nahla Abdo","id":"nahla-abdo"},{"name":"Gregory Brown","id":"gregory-brown"},{"name":"Alex Bing","id":"alex-bing"},{"name":" ","id":" "},{"name":"Davorka Ljubisic","id":"davorka-ljubisic"},{"name":"Shuchi Karim","id":"shuchi-karim"},{"name":"Xiaobei Chen","id":"xiaobei-chen"},{"name":"Ariel Fuenzalida","id":"ariel-fuenzalida"},{"name":"Megan Graham","id":"megan-graham"},{"name":"Amina Mire","id":"amina-mire"}]