[{"id":"TIMG5001-T","courseId":"TIMG5001","section":"T","term":"","type":"Seminar","startDate":"2024-01-08","endDate":"2024-04-10","days":[{"day":[],"startTime":"","endTime":"","building":"","room":""},{"day":["Wed"],"startTime":"18:05","endTime":"20:55","building":" Nicol Building","room":" 3020"}],"staffId":"nusa-fain","physicality":"IN-PERSON","registrationAdditions":[]},{"id":"TIMG5002-A","courseId":"TIMG5002","section":"A","term":"","type":"Seminar","startDate":"2024-01-08","endDate":"2024-04-10","days":[{"day":[],"startTime":"","endTime":"","building":"","room":""},{"day":["Thu"],"startTime":"18:05","endTime":"20:55","building":" Nicol Building","room":" 3030"}],"staffId":"eduardo-bailetti","physicality":"IN-PERSON","registrationAdditions":[]},{"id":"TIMG5003-A","courseId":"TIMG5003","section":"A","term":"","type":"Seminar","startDate":"2024-01-08","endDate":"2024-04-10","days":[{"day":[],"startTime":"","endTime":"","building":"","room":""},{"day":["Tue"],"startTime":"18:05","endTime":"20:55","building":" Nicol Building","room":" 3020"}],"staffId":"mika-westerlund","physicality":"IN-PERSON","registrationAdditions":[]},{"id":"TIMG5006-A","courseId":"TIMG5006","section":"A","term":"","type":"Seminar","startDate":"2024-01-08","endDate":"2024-04-10","days":[{"day":[],"startTime":"","endTime":"","building":"","room":""},{"day":["Tue"],"startTime":"18:05","endTime":"20:55","building":" Nicol Building","room":" 4010"}],"staffId":"michael-weiss","physicality":"IN-PERSON","registrationAdditions":[]},{"id":"TIMG5008-A","courseId":"TIMG5008","section":"A","term":"","type":"Seminar","startDate":"2024-01-08","endDate":"2024-04-10","days":[{"day":[],"startTime":"","endTime":"","building":"","room":""},{"day":["Wed"],"startTime":"18:05","endTime":"20:55","building":" St. Patrick's Building","room":" 100"}],"staffId":"stoyan-tanev","physicality":"IN-PERSON","registrationAdditions":[]},{"id":"TIMG5103-B","courseId":"TIMG5103","section":"B","term":"","type":"Seminar","startDate":"2024-01-08","endDate":"2024-04-10","days":[{"day":[],"startTime":"","endTime":"","building":"","room":""},{"day":["Fri"],"startTime":"14:35","endTime":"17:25","building":" Nicol Building","room":" 4050"}],"staffId":" ","physicality":"IN-PERSON","registrationAdditions":[]},{"id":"TIMG5103-P","courseId":"TIMG5103","section":"P","term":"","type":"Seminar","startDate":"2024-01-08","endDate":"2024-04-10","days":[{"day":[],"startTime":"","endTime":"","building":"","room":""},{"day":["Fri"],"startTime":"14:35","endTime":"17:25","building":" Nicol Building","room":" 3020"}],"staffId":"nusa-fain","physicality":"IN-PERSON","registrationAdditions":[]},{"id":"TIMG5103-W","courseId":"TIMG5103","section":"W","term":"","type":"Seminar","startDate":"2024-01-08","endDate":"2024-04-10","days":[{"day":[],"startTime":"","endTime":"","building":"","room":""},{"day":["Fri"],"startTime":"14:35","endTime":"17:25","building":" Nicol Building","room":" 3038"}],"staffId":"nusa-fain","physicality":"IN-PERSON","registrationAdditions":[]},{"id":"TIMG5104-A","courseId":"TIMG5104","section":"A","term":"","type":"Directed Studies","startDate":"2024-01-08","endDate":"2024-04-10","days":[{"day":[],"startTime":"","endTime":"","building":"","room":""},{"day":[""],"startTime":null,"endTime":null,"building":null,"room":null}],"staffId":"tony-bailetti","physicality":"IN-PERSON","registrationAdditions":[]},{"id":"TIMG5201-A","courseId":"TIMG5201","section":"A","term":"","type":"Seminar","startDate":"2024-01-08","endDate":"2024-04-10","days":[{"day":[],"startTime":"","endTime":"","building":"","room":""},{"day":["Thu"],"startTime":"18:05","endTime":"20:55","building":" Nicol Building","room":" 3020"}],"staffId":"tony-bailetti","physicality":"IN-PERSON","registrationAdditions":[]},{"id":"TIMG5203-A","courseId":"TIMG5203","section":"A","term":"","type":"Seminar","startDate":"2024-01-08","endDate":"2024-04-10","days":[{"day":[],"startTime":"","endTime":"","building":"","room":""},{"day":["Mon"],"startTime":"18:05","endTime":"20:55","building":" Nicol Building","room":" 4030"}],"staffId":"tony-bailetti","physicality":"IN-PERSON","registrationAdditions":[]},{"id":"TIMG5303-A","courseId":"TIMG5303","section":"A","term":"","type":"Seminar","startDate":"2024-01-08","endDate":"2024-04-10","days":[{"day":[],"startTime":"","endTime":"","building":"","room":""},{"day":["Mon"],"startTime":"18:05","endTime":"20:55","building":" Nicol Building","room":" 3020"}],"staffId":"mika-westerlund","physicality":"IN-PERSON","registrationAdditions":[]},{"id":"TIMG5901-T","courseId":"TIMG5901","section":"T","term":"","type":"Research Project","startDate":"2024-01-08","endDate":"2024-04-10","days":[{"day":[],"startTime":"","endTime":"","building":"","room":""},{"day":[""],"startTime":null,"endTime":null,"building":null,"room":null}],"staffId":"tony-bailetti","physicality":"ONLINE","registrationAdditions":[]},{"id":"TIMG5905-W","courseId":"TIMG5905","section":"W","term":"","type":"Research Project","startDate":"2024-01-08","endDate":"2024-04-10","days":[{"day":[],"startTime":"","endTime":"","building":"","room":""},{"day":[""],"startTime":null,"endTime":null,"building":null,"room":null}],"staffId":"tony-bailetti","physicality":"ONLINE","registrationAdditions":[]},{"id":"TIMG5907-A","courseId":"TIMG5907","section":"A","term":"","type":"Research Project","startDate":"2024-01-08","endDate":"2024-04-10","days":[{"day":[],"startTime":"","endTime":"","building":"","room":""},{"day":[""],"startTime":null,"endTime":null,"building":null,"room":null}],"staffId":"tony-bailetti","physicality":"ONLINE","registrationAdditions":[]},{"id":"TIMG5908-A","courseId":"TIMG5908","section":"A","term":"","type":"Research Project","startDate":"2024-01-08","endDate":"2024-04-10","days":[{"day":[],"startTime":"","endTime":"","building":"","room":""},{"day":[""],"startTime":null,"endTime":null,"building":null,"room":null}],"staffId":"tony-bailetti","physicality":"ONLINE","registrationAdditions":[]},{"id":"TIMG5909-T","courseId":"TIMG5909","section":"T","term":"","type":"Masters Thesis","startDate":"2024-01-08","endDate":"2024-04-10","days":[{"day":[],"startTime":"","endTime":"","building":"","room":""},{"day":[""],"startTime":null,"endTime":null,"building":null,"room":null}],"staffId":"tony-bailetti","physicality":"ONLINE","registrationAdditions":[]}]